zacro-1.0.12.dist-info/RECORD
zacro-1.0.12.dist-info/WHEEL
zacro-1.0.12.dist-info/entry_points.txt
zacro-1.0.12.dist-info/METADATA
zacro-1.0.12.dist-info/licenses/LICENSE
zacro/tree.py
zacro/zacro.cpython-311-darwin.so
zacro/__init__.py
zacro/cli.py
