Metadata-Version: 2.4
Name: zacro
Version: 1.0.12
Classifier: Development Status :: 3 - Alpha
Classifier: Intended Audience :: Developers
Classifier: License :: OSI Approved :: MIT License
Classifier: Programming Language :: Python :: 3
Classifier: Programming Language :: Python :: 3.8
Classifier: Programming Language :: Python :: 3.9
Classifier: Programming Language :: Python :: 3.10
Classifier: Programming Language :: Python :: 3.11
Classifier: Programming Language :: Python :: 3.12
Classifier: Programming Language :: Rust
Classifier: Topic :: Software Development :: Libraries :: Python Modules
Requires-Dist: pytest ; extra == 'test'
Requires-Dist: pytest-cov ; extra == 'test'
Requires-Dist: black ; extra == 'dev'
Requires-Dist: isort ; extra == 'dev'
Requires-Dist: flake8 ; extra == 'dev'
Requires-Dist: maturin ; extra == 'dev'
Provides-Extra: test
Provides-Extra: dev
License-File: LICENSE
Summary: Fast Rust implementation of xacro with enhanced features for modular robotics
Author: Iori Yanokura
License: MIT
Requires-Python: >=3.8
Project-URL: Repository, https://github.com/iory/zacro
